teamod/_TEA.py
teamod/__init__.py
teamod-0.0.1.dist-info/LICENSE
teamod-0.0.1.dist-info/METADATA
teamod-0.0.1.dist-info/WHEEL
teamod-0.0.1.dist-info/top_level.txt
teamod-0.0.1.dist-info/RECORD
